bypassmappingproxy.py
bypassmappingproxy-0.1.0.dist-info/METADATA
bypassmappingproxy-0.1.0.dist-info/WHEEL
bypassmappingproxy-0.1.0.dist-info/top_level.txt
bypassmappingproxy-0.1.0.dist-info/RECORD
