Metadata-Version: 2.1
Name: bypassmappingproxy
Version: 0.1.0
Summary: modify immutable types by bypassing mapping proxy
